odoo/addons/contract_sale_invoicing/README.rst
odoo/addons/contract_sale_invoicing/__init__.py
odoo/addons/contract_sale_invoicing/__manifest__.py
odoo/addons/contract_sale_invoicing/i18n/ca.po
odoo/addons/contract_sale_invoicing/i18n/contract_sale_invoicing.pot
odoo/addons/contract_sale_invoicing/i18n/de.po
odoo/addons/contract_sale_invoicing/i18n/el_GR.po
odoo/addons/contract_sale_invoicing/i18n/es.po
odoo/addons/contract_sale_invoicing/i18n/es_CL.po
odoo/addons/contract_sale_invoicing/i18n/es_MX.po
odoo/addons/contract_sale_invoicing/i18n/fi.po
odoo/addons/contract_sale_invoicing/i18n/fr.po
odoo/addons/contract_sale_invoicing/i18n/gl.po
odoo/addons/contract_sale_invoicing/i18n/hi_IN.po
odoo/addons/contract_sale_invoicing/i18n/hr.po
odoo/addons/contract_sale_invoicing/i18n/hr_HR.po
odoo/addons/contract_sale_invoicing/i18n/hu.po
odoo/addons/contract_sale_invoicing/i18n/it.po
odoo/addons/contract_sale_invoicing/i18n/nl.po
odoo/addons/contract_sale_invoicing/i18n/pt.po
odoo/addons/contract_sale_invoicing/i18n/pt_BR.po
odoo/addons/contract_sale_invoicing/i18n/pt_PT.po
odoo/addons/contract_sale_invoicing/i18n/ro.po
odoo/addons/contract_sale_invoicing/i18n/sk_SK.po
odoo/addons/contract_sale_invoicing/i18n/sl.po
odoo/addons/contract_sale_invoicing/i18n/tr.po
odoo/addons/contract_sale_invoicing/i18n/tr_TR.po
odoo/addons/contract_sale_invoicing/i18n/zh.po
odoo/addons/contract_sale_invoicing/i18n/zh_CN.po
odoo/addons/contract_sale_invoicing/models/__init__.py
odoo/addons/contract_sale_invoicing/models/contract.py
odoo/addons/contract_sale_invoicing/readme/CONTRIBUTORS.rst
odoo/addons/contract_sale_invoicing/readme/DESCRIPTION.rst
odoo/addons/contract_sale_invoicing/readme/USAGE.rst
odoo/addons/contract_sale_invoicing/static/description/icon.png
odoo/addons/contract_sale_invoicing/static/description/index.html
odoo/addons/contract_sale_invoicing/tests/__init__.py
odoo/addons/contract_sale_invoicing/tests/test_contract_sale_invoicing.py
odoo12_addon_contract_sale_invoicing-12.0.1.0.4.dist-info/METADATA
odoo12_addon_contract_sale_invoicing-12.0.1.0.4.dist-info/WHEEL
odoo12_addon_contract_sale_invoicing-12.0.1.0.4.dist-info/top_level.txt
odoo12_addon_contract_sale_invoicing-12.0.1.0.4.dist-info/RECORD
